NFSyndication-0.2.25.dist-info/RECORD
NFSyndication-0.2.25.dist-info/WHEEL
NFSyndication-0.2.25.dist-info/DESCRIPTION.rst
NFSyndication-0.2.25.dist-info/entry_points.txt
NFSyndication-0.2.25.dist-info/METADATA
NFSyndication-0.2.25.dist-info/metadata.json
NFSyndication-0.2.25.dist-info/top_level.txt
tests/nfs_module_test.py
tests/conf_test.py
tests/__init__.py
NFSyndication/config.py
NFSyndication/nfs_main.py
NFSyndication/utils.py
NFSyndication/extras.py
NFSyndication/styles.py
NFSyndication/__main__.py
NFSyndication/__init__.py
NFSyndication/templates/_layout.html
NFSyndication/templates/static/style.css
NFSyndication/core/__init__.py
