Metadata-Version: 2.0
Name: NFSyndication
Version: 0.2.25
Summary: News Feed Syndication - A package that read and fetch RSS feeds from the publications.
Home-page: UNKNOWN
Author: Web SRC
Author-email: web.system.management@gmail.com
License: BSD-2-Clause
Project-URL: Source, https://github.com/web-sys1/NFSyndication/
Keywords: rss,news
Platform: UNKNOWN
Classifier: Development Status :: 3 - Alpha
Classifier: Development Status :: 4 - Beta
Classifier: Environment :: Web Environment
Classifier: Intended Audience :: Developers
Classifier: License :: OSI Approved :: BSD License
Classifier: Operating System :: OS Independent
Classifier: Programming Language :: Python :: 3
Classifier: Programming Language :: Python :: 3.6
Classifier: Programming Language :: Python :: 3.7
Classifier: Programming Language :: Python :: 3.8
Classifier: Topic :: Internet :: WWW/HTTP :: Dynamic Content
Classifier: Topic :: Software Development :: Libraries :: Python Modules
Classifier: Topic :: Text Processing :: Markup :: HTML
Provides-Extra: test
Requires-Dist: colorama (==0.4.4)
Requires-Dist: colorful (==0.5.4)
Requires-Dist: cssutils
Requires-Dist: feedparser (==6.0.2)
Requires-Dist: Jinja2 (==2.11.3)
Requires-Dist: configparser (==5.0.2)
Requires-Dist: pytz (>=2017.2)
Requires-Dist: wheel (==0.24.0)
Provides-Extra: test
Requires-Dist: multipart; extra == 'test'
Requires-Dist: flask; extra == 'test'
Requires-Dist: pre-commit; extra == 'test'
Requires-Dist: pytest; extra == 'test'
Requires-Dist: pytest-cov; extra == 'test'
Requires-Dist: pigments; extra == 'test'
Requires-Dist: requests-toolbelt; extra == 'test'
Requires-Dist: responses (>=0.11.0); extra == 'test'
Requires-Dist: tornado; extra == 'test'
Requires-Dist: twine; extra == 'test'
